hide_info/__init__.py
hide_info/echo_watermark.py
hide_info/evaluate.py
hide_info/hide_as_img.py
hide_info/hide_as_music.py
hide_info/hide_as_txt.py
hide_info/hide_in_img.py
hide_info/hide_in_music.py
hide_info/hide_in_txt.py
hide_info/img_exif.py
hide_info/img_seed.py
hide_info/img_watermark.py
hide_info/mirage_tank.py
hide_info/utils.py
HideInfo-0.1.9.dist-info/LICENSE
HideInfo-0.1.9.dist-info/METADATA
HideInfo-0.1.9.dist-info/WHEEL
HideInfo-0.1.9.dist-info/top_level.txt
HideInfo-0.1.9.dist-info/RECORD
