Metadata-Version: 2.1
Name: HideInfo
Version: 0.1.9
Summary: Info Hiding Library，一些信息隐藏技术
Home-page: https://github.com/guofei9987/cloakware
Author: Guo Fei
Author-email: guofei9987@foxmail.com
License: MIT
Platform: linux
Platform: windows
Platform: macos
Requires-Python: >=3.5
License-File: LICENSE
Requires-Dist: setuptools
Requires-Dist: numpy
Requires-Dist: Pillow
Requires-Dist: opencv-python
Requires-Dist: scipy
Requires-Dist: piexif
